{
    "Orange": {
        "totalActive": 144,
        "totalInactive": 4,
        "totalNewDelivered": 148,
        "totalNewUndelivered": 4
    },
    "Red": {
        "totalOldActive": 146,
        "totalOldInactive": 6,
        "totalNewDelivered": 48,
        "totalNewUndelivered": 204
    },
    "Green": {
        "totalType7Active": 84,
        "totalType7Inactive": 19,
        "totalType8Active": 76,
        "totalType8Inactive": 18,
        "totalType9Active": 24,
        "totalType9Inactive": 0,
        "totalType10Delivered": 0,
        "totalType10Undelivered": 102
    },
    "Blue": {
        "totalActive": 94,
        "totalInactive": 0
    },
    "Mattapan": {
        "totalActive": 7,
        "totalInactive": 3
    },
    "Sources": {
        "fleet_numbers": "http://roster.transithistory.org/",
        "carriage_ages": "http://roster.transithistory.org/"
    },
    "Updated": "2025-12-23"
}
